MANIFEST.in
README.md
README.rst
requirements.txt
setup.py
pytab/__init__.py
pytab/table.py
pytab.egg-info/PKG-INFO
pytab.egg-info/SOURCES.txt
pytab.egg-info/dependency_links.txt
pytab.egg-info/requires.txt
pytab.egg-info/top_level.txt