Metadata-Version: 1.2
Name: pytab
Version: 1.0.4
Summary: pyTable is the library to plot table easily!
Home-page: https://github.com/HiroshiARAKI/pytable
Author: Hiroshi ARAKI
Author-email: araki@hirlab.net
Maintainer: Hiroshi ARAKI
Maintainer-email: araki@hirlab.net
License: MIT
Platform: UNKNOWN
Classifier: Programming Language :: Python :: 3
Classifier: Programming Language :: Python :: 3.5
Classifier: Programming Language :: Python :: 3.6
Classifier: Programming Language :: Python :: 3.7
Classifier: Programming Language :: Python :: 3.8
Classifier: License :: OSI Approved :: MIT License
